viswa_friend/__init__.py
viswa_friend/project.py
viswa_friend-2.0.dist-info/METADATA
viswa_friend-2.0.dist-info/WHEEL
viswa_friend-2.0.dist-info/top_level.txt
viswa_friend-2.0.dist-info/RECORD
