Metadata-Version: 2.1
Name: viswa-friend
Version: 2.0
Summary: viswa 🤝 is a loyal friend who always has your back. He's the kind of friend who will drop everything to help you out, no questions asked. 🎉 He's the friend who makes every moment together unforgettable.
Home-page: UNKNOWN
License: UNKNOWN
Platform: UNKNOWN
